irmlearn/__init__.py
irmlearn/__version__.py
irmlearn/irm.py
irmlearn/utils.py
irmlearn-0.0.1b1.dist-info/LICENSE
irmlearn-0.0.1b1.dist-info/METADATA
irmlearn-0.0.1b1.dist-info/WHEEL
irmlearn-0.0.1b1.dist-info/top_level.txt
irmlearn-0.0.1b1.dist-info/RECORD
