Metadata-Version: 2.1
Name: irmlearn
Version: 0.0.1b1
Summary: Infinite Relational Model in Python with scikit-learn like API.
Home-page: https://github.com/ground0state/irmlearn
Author: Masafumi Abeta
Author-email: ground0state@gmail.com
License: MIT
Platform: UNKNOWN
Classifier: Development Status :: 3 - Alpha
Classifier: License :: OSI Approved :: MIT License
Classifier: Intended Audience :: Developers
Classifier: Intended Audience :: Science/Research
Classifier: Topic :: Software Development
Classifier: Topic :: Scientific/Engineering
Classifier: Programming Language :: Python
Classifier: Programming Language :: Python :: 3
License-File: LICENSE
Requires-Dist: numpy
Requires-Dist: scipy
Requires-Dist: scikit-learn
